hdf5storage/__init__.py
hdf5storage/exceptions.py
hdf5storage/marshallers.py
hdf5storage/pathesc.py
hdf5storage/plugins.py
hdf5storage/utilities.py
hdf5storage-0.2.1.dist-info/COPYING.txt
hdf5storage-0.2.1.dist-info/METADATA
hdf5storage-0.2.1.dist-info/WHEEL
hdf5storage-0.2.1.dist-info/RECORD
