Metadata-Version: 2.3
Name: hdf5storage
Version: 0.2.1
Summary: Utilities to read/write Python types to/from HDF5 files, including MATLAB v7.3 MAT files.
License: BSD
Keywords: hdf5,matlab
Author: Freja Nordsiek
Author-email: fnordsie@posteo.net
Maintainer: Jesse R Codling
Maintainer-email: codling@umich.edu
Requires-Python: >=3.10,<4.0
Classifier: Programming Language :: Python :: 3 :: Only
Classifier: Development Status :: 3 - Alpha
Classifier: License :: OSI Approved :: BSD License
Classifier: Operating System :: OS Independent
Classifier: Intended Audience :: Developers
Classifier: Intended Audience :: Information Technology
Classifier: Intended Audience :: Science/Research
Classifier: Topic :: Scientific/Engineering
Classifier: Topic :: Database
Classifier: Topic :: Software Development :: Libraries :: Python Modules
Provides-Extra: dev
Provides-Extra: docs
Provides-Extra: scipy
Provides-Extra: tests
Requires-Dist: deptry (>=0.23.0) ; extra == "dev"
Requires-Dist: deptry (>=0.23.0) ; extra == "tests"
Requires-Dist: h5py (>=3.9)
Requires-Dist: numpy (>=1.26)
Requires-Dist: pytest (>=8.3) ; extra == "dev"
Requires-Dist: pytest (>=8.3) ; extra == "tests"
Requires-Dist: ruff (>=0.9) ; extra == "dev"
Requires-Dist: ruff (>=0.9) ; extra == "tests"
Requires-Dist: scipy (>=1.14.0) ; extra == "dev"
Requires-Dist: scipy (>=1.14.0) ; extra == "scipy"
Requires-Dist: sphinx (>=8.0) ; extra == "dev"
Requires-Dist: sphinx (>=8.0) ; extra == "docs"
Requires-Dist: sphinx_rtd_theme (>=3.0) ; extra == "dev"
Requires-Dist: sphinx_rtd_theme (>=3.0) ; extra == "docs"
